{
  "source": "google-trends-id",
  "lastUpdated": "2026-05-13T01:23:54.458Z",
  "items": [
    {
      "title": "al-nassr vs al-hilal",
      "link": "https://trends.google.com/trending/rss?geo=ID",
      "pubDate": "2026-05-13T01:23:54.458Z",
      "approxTraffic": "200K+",
      "started": "13 hours ago",
      "source": "browser-scrape"
    },
    {
      "title": "osasuna vs atlético madrid",
      "link": "https://trends.google.com/trending/rss?geo=ID",
      "pubDate": "2026-05-13T01:23:54.458Z",
      "approxTraffic": "20K+",
      "started": "14 hours ago",
      "source": "browser-scrape"
    },
    {
      "title": "betis vs elche",
      "link": "https://trends.google.com/trending/rss?geo=ID",
      "pubDate": "2026-05-13T01:23:54.458Z",
      "approxTraffic": "20K+",
      "started": "8 hours ago",
      "source": "browser-scrape"
    },
    {
      "title": "usd idr",
      "link": "https://trends.google.com/trending/rss?geo=ID",
      "pubDate": "2026-05-13T01:23:54.458Z",
      "approxTraffic": "50K+",
      "started": "23 hours ago",
      "source": "browser-scrape"
    },
    {
      "title": "celta vs levante",
      "link": "https://trends.google.com/trending/rss?geo=ID",
      "pubDate": "2026-05-13T01:23:54.458Z",
      "approxTraffic": "20K+",
      "started": "12 hours ago",
      "source": "browser-scrape"
    },
    {
      "title": "southampton vs middlesbrough",
      "link": "https://trends.google.com/trending/rss?geo=ID",
      "pubDate": "2026-05-13T01:23:54.458Z",
      "approxTraffic": "10K+",
      "started": "14 hours ago",
      "source": "browser-scrape"
    },
    {
      "title": "bmkg",
      "link": "https://trends.google.com/trending/rss?geo=ID",
      "pubDate": "2026-05-13T01:23:54.458Z",
      "approxTraffic": "200K+",
      "started": "14 hours ago",
      "source": "browser-scrape"
    },
    {
      "title": "indonesia vs jepang u17",
      "link": "https://trends.google.com/trending/rss?geo=ID",
      "pubDate": "2026-05-13T01:23:54.458Z",
      "approxTraffic": "20K+",
      "started": "14 hours ago",
      "source": "browser-scrape"
    },
    {
      "title": "bolivia",
      "link": "https://trends.google.com/trending/rss?geo=ID",
      "pubDate": "2026-05-13T01:23:54.458Z",
      "approxTraffic": "5K+",
      "started": "9 hours ago",
      "source": "browser-scrape"
    },
    {
      "title": "pengumuman msci saham",
      "link": "https://trends.google.com/trending/rss?geo=ID",
      "pubDate": "2026-05-13T01:23:54.458Z",
      "approxTraffic": "5K+",
      "started": "21 hours ago",
      "source": "browser-scrape"
    },
    {
      "title": "christian nørgaard",
      "link": "https://trends.google.com/trending/rss?geo=ID",
      "pubDate": "2026-05-13T01:23:54.458Z",
      "approxTraffic": "5K+",
      "started": "12 hours ago",
      "source": "browser-scrape"
    },
    {
      "title": "donald trump",
      "link": "https://trends.google.com/trending/rss?geo=ID",
      "pubDate": "2026-05-13T01:23:54.458Z",
      "approxTraffic": "5K+",
      "started": "20 hours ago",
      "source": "browser-scrape"
    },
    {
      "title": "bupati inisial r",
      "link": "https://trends.google.com/trending/rss?geo=ID",
      "pubDate": "2026-05-13T01:23:54.458Z",
      "approxTraffic": "5K+",
      "started": "21 hours ago",
      "source": "browser-scrape"
    },
    {
      "title": "brandon clarke",
      "link": "https://trends.google.com/trending/rss?geo=ID",
      "pubDate": "2026-05-13T01:23:54.458Z",
      "approxTraffic": "2K+",
      "started": "7 hours ago",
      "source": "browser-scrape"
    },
    {
      "title": "surya semesta internusa",
      "link": "https://trends.google.com/trending/rss?geo=ID",
      "pubDate": "2026-05-13T01:23:54.458Z",
      "approxTraffic": "2K+",
      "started": "13 hours ago",
      "source": "browser-scrape"
    }
  ]
}
