{
  "source": "google-trends-id",
  "lastUpdated": "2026-05-31T02:24:49.477Z",
  "items": [
    {
      "title": "tempat menonton psg vs arsenal",
      "link": "https://trends.google.com/trending/rss?geo=ID",
      "pubDate": "2026-05-31T02:24:49.477Z",
      "approxTraffic": "500K+",
      "started": "10 hours ago",
      "source": "browser-scrape"
    },
    {
      "title": "malaysia",
      "link": "https://trends.google.com/trending/rss?geo=ID",
      "pubDate": "2026-05-31T02:24:49.477Z",
      "approxTraffic": "50K+",
      "started": "22 hours ago",
      "source": "browser-scrape"
    },
    {
      "title": "ekuador vs arab saudi",
      "link": "https://trends.google.com/trending/rss?geo=ID",
      "pubDate": "2026-05-31T02:24:49.477Z",
      "approxTraffic": "10K+",
      "started": "3 hours ago",
      "source": "browser-scrape"
    },
    {
      "title": "fifa",
      "link": "https://trends.google.com/trending/rss?geo=ID",
      "pubDate": "2026-05-31T02:24:49.477Z",
      "approxTraffic": "10K+",
      "started": "22 hours ago",
      "source": "browser-scrape"
    },
    {
      "title": "matvey safonov",
      "link": "https://trends.google.com/trending/rss?geo=ID",
      "pubDate": "2026-05-31T02:24:49.477Z",
      "approxTraffic": "20K+",
      "started": "11 hours ago",
      "source": "browser-scrape"
    },
    {
      "title": "thunder vs spurs",
      "link": "https://trends.google.com/trending/rss?geo=ID",
      "pubDate": "2026-05-31T02:24:49.477Z",
      "approxTraffic": "10K+",
      "started": "2 hours ago",
      "source": "browser-scrape"
    },
    {
      "title": "andoni iraola",
      "link": "https://trends.google.com/trending/rss?geo=ID",
      "pubDate": "2026-05-31T02:24:49.477Z",
      "approxTraffic": "10K+",
      "started": "15 hours ago",
      "source": "browser-scrape"
    },
    {
      "title": "santos vs vitória",
      "link": "https://trends.google.com/trending/rss?geo=ID",
      "pubDate": "2026-05-31T02:24:49.477Z",
      "approxTraffic": "5K+",
      "started": "3 hours ago",
      "source": "browser-scrape"
    },
    {
      "title": "fabian ruiz",
      "link": "https://trends.google.com/trending/rss?geo=ID",
      "pubDate": "2026-05-31T02:24:49.477Z",
      "approxTraffic": "5K+",
      "started": "11 hours ago",
      "source": "browser-scrape"
    },
    {
      "title": "perdagangan elektronik",
      "link": "https://trends.google.com/trending/rss?geo=ID",
      "pubDate": "2026-05-31T02:24:49.477Z",
      "approxTraffic": "5K+",
      "started": "17 hours ago",
      "source": "browser-scrape"
    },
    {
      "title": "david raya",
      "link": "https://trends.google.com/trending/rss?geo=ID",
      "pubDate": "2026-05-31T02:24:49.477Z",
      "approxTraffic": "20K+",
      "started": "11 hours ago",
      "source": "browser-scrape"
    },
    {
      "title": "champions league final",
      "link": "https://trends.google.com/trending/rss?geo=ID",
      "pubDate": "2026-05-31T02:24:49.477Z",
      "approxTraffic": "50K+",
      "started": "16 hours ago",
      "source": "browser-scrape"
    },
    {
      "title": "meksiko vs australia",
      "link": "https://trends.google.com/trending/rss?geo=ID",
      "pubDate": "2026-05-31T02:24:49.477Z",
      "approxTraffic": "2K+",
      "started": "40 minutes ago",
      "source": "browser-scrape"
    },
    {
      "title": "khvicha kvaratskhelia",
      "link": "https://trends.google.com/trending/rss?geo=ID",
      "pubDate": "2026-05-31T02:24:49.477Z",
      "approxTraffic": "5K+",
      "started": "11 hours ago",
      "source": "browser-scrape"
    },
    {
      "title": "psg",
      "link": "https://trends.google.com/trending/rss?geo=ID",
      "pubDate": "2026-05-31T02:24:49.477Z",
      "approxTraffic": "100K+",
      "started": "10 hours ago",
      "source": "browser-scrape"
    }
  ]
}
