{
  "source": "google-trends-id",
  "lastUpdated": "2026-05-03T11:49:49.094Z",
  "items": [
    {
      "title": "bayern vs heidenheim",
      "link": "https://trends.google.com/trending/rss?geo=ID",
      "pubDate": "2026-05-03T11:49:49.094Z",
      "approxTraffic": "200K+",
      "started": "23 hours ago",
      "source": "browser-scrape"
    },
    {
      "title": "psg vs lorient",
      "link": "https://trends.google.com/trending/rss?geo=ID",
      "pubDate": "2026-05-03T11:49:49.094Z",
      "approxTraffic": "100K+",
      "started": "23 hours ago",
      "source": "browser-scrape"
    },
    {
      "title": "arema vs persik",
      "link": "https://trends.google.com/trending/rss?geo=ID",
      "pubDate": "2026-05-03T11:49:49.094Z",
      "approxTraffic": "50K+",
      "started": "5 hours ago",
      "source": "browser-scrape"
    },
    {
      "title": "inter miami vs orlando city",
      "link": "https://trends.google.com/trending/rss?geo=ID",
      "pubDate": "2026-05-03T11:49:49.094Z",
      "approxTraffic": "20K+",
      "started": "11 hours ago",
      "source": "browser-scrape"
    },
    {
      "title": "liga 2",
      "link": "https://trends.google.com/trending/rss?geo=ID",
      "pubDate": "2026-05-03T11:49:49.094Z",
      "approxTraffic": "50K+",
      "started": "3 hours ago",
      "source": "browser-scrape"
    },
    {
      "title": "wolves vs sunderland",
      "link": "https://trends.google.com/trending/rss?geo=ID",
      "pubDate": "2026-05-03T11:49:49.094Z",
      "approxTraffic": "20K+",
      "started": "22 hours ago",
      "source": "browser-scrape"
    },
    {
      "title": "klasemen brentford vs west ham",
      "link": "https://trends.google.com/trending/rss?geo=ID",
      "pubDate": "2026-05-03T11:49:49.094Z",
      "approxTraffic": "20K+",
      "started": "19 hours ago",
      "source": "browser-scrape"
    },
    {
      "title": "samsunspor vs galatasaray",
      "link": "https://trends.google.com/trending/rss?geo=ID",
      "pubDate": "2026-05-03T11:49:49.094Z",
      "approxTraffic": "5K+",
      "started": "50 minutes ago",
      "source": "browser-scrape"
    },
    {
      "title": "purbaya yudhi sadewa",
      "link": "https://trends.google.com/trending/rss?geo=ID",
      "pubDate": "2026-05-03T11:49:49.094Z",
      "approxTraffic": "10K+",
      "started": "14 hours ago",
      "source": "browser-scrape"
    },
    {
      "title": "persipura",
      "link": "https://trends.google.com/trending/rss?geo=ID",
      "pubDate": "2026-05-03T11:49:49.094Z",
      "approxTraffic": "10K+",
      "started": "3 hours ago",
      "source": "browser-scrape"
    },
    {
      "title": "klasemen como vs napoli",
      "link": "https://trends.google.com/trending/rss?geo=ID",
      "pubDate": "2026-05-03T11:49:49.094Z",
      "approxTraffic": "10K+",
      "started": "17 hours ago",
      "source": "browser-scrape"
    },
    {
      "title": "renault triber",
      "link": "https://trends.google.com/trending/rss?geo=ID",
      "pubDate": "2026-05-03T11:49:49.094Z",
      "approxTraffic": "5K+",
      "started": "20 hours ago",
      "source": "browser-scrape"
    },
    {
      "title": "pss",
      "link": "https://trends.google.com/trending/rss?geo=ID",
      "pubDate": "2026-05-03T11:49:49.094Z",
      "approxTraffic": "5K+",
      "started": "4 hours ago",
      "source": "browser-scrape"
    },
    {
      "title": "ajax vs psv",
      "link": "https://trends.google.com/trending/rss?geo=ID",
      "pubDate": "2026-05-03T11:49:49.094Z",
      "approxTraffic": "10K+",
      "started": "18 hours ago",
      "source": "browser-scrape"
    },
    {
      "title": "hujan deras",
      "link": "https://trends.google.com/trending/rss?geo=ID",
      "pubDate": "2026-05-03T11:49:49.094Z",
      "approxTraffic": "2K+",
      "started": "8 hours ago",
      "source": "browser-scrape"
    }
  ]
}
