{
  "source": "google-trends-id",
  "lastUpdated": "2026-04-21T08:18:25.619Z",
  "items": [
    {
      "title": "dewa united vs persib bandung",
      "link": "https://trends.google.com/trending/rss?geo=ID",
      "pubDate": "2026-04-21T08:18:25.619Z",
      "approxTraffic": "500K+",
      "started": "23 hours ago",
      "source": "browser-scrape"
    },
    {
      "title": "crystal palace vs west ham",
      "link": "https://trends.google.com/trending/rss?geo=ID",
      "pubDate": "2026-04-21T08:18:25.619Z",
      "approxTraffic": "50K+",
      "started": "22 hours ago",
      "source": "browser-scrape"
    },
    {
      "title": "jepang",
      "link": "https://trends.google.com/trending/rss?geo=ID",
      "pubDate": "2026-04-21T08:18:25.619Z",
      "approxTraffic": "50K+",
      "started": "22 hours ago",
      "source": "browser-scrape"
    },
    {
      "title": "kilang minyak",
      "link": "https://trends.google.com/trending/rss?geo=ID",
      "pubDate": "2026-04-21T08:18:25.619Z",
      "approxTraffic": "10K+",
      "started": "23 hours ago",
      "source": "browser-scrape"
    },
    {
      "title": "lecce vs fiorentina",
      "link": "https://trends.google.com/trending/rss?geo=ID",
      "pubDate": "2026-04-21T08:18:25.619Z",
      "approxTraffic": "20K+",
      "started": "22 hours ago",
      "source": "browser-scrape"
    },
    {
      "title": "pss vs persiku",
      "link": "https://trends.google.com/trending/rss?geo=ID",
      "pubDate": "2026-04-21T08:18:25.619Z",
      "approxTraffic": "20K+",
      "started": "20 hours ago",
      "source": "browser-scrape"
    },
    {
      "title": "ucapan selamat hari kartini",
      "link": "https://trends.google.com/trending/rss?geo=ID",
      "pubDate": "2026-04-21T08:18:25.619Z",
      "approxTraffic": "20K+",
      "started": "8 hours ago",
      "source": "browser-scrape"
    },
    {
      "title": "tarif listrik",
      "link": "https://trends.google.com/trending/rss?geo=ID",
      "pubDate": "2026-04-21T08:18:25.619Z",
      "approxTraffic": "10K+",
      "started": "23 hours ago",
      "source": "browser-scrape"
    },
    {
      "title": "harga pertalite april 2026",
      "link": "https://trends.google.com/trending/rss?geo=ID",
      "pubDate": "2026-04-21T08:18:25.619Z",
      "approxTraffic": "10K+",
      "started": "19 hours ago",
      "source": "browser-scrape"
    },
    {
      "title": "john ternus",
      "link": "https://trends.google.com/trending/rss?geo=ID",
      "pubDate": "2026-04-21T08:18:25.619Z",
      "approxTraffic": "5K+",
      "started": "9 hours ago",
      "source": "browser-scrape"
    },
    {
      "title": "donald trump",
      "link": "https://trends.google.com/trending/rss?geo=ID",
      "pubDate": "2026-04-21T08:18:25.619Z",
      "approxTraffic": "5K+",
      "started": "14 hours ago",
      "source": "browser-scrape"
    },
    {
      "title": "msci",
      "link": "https://trends.google.com/trending/rss?geo=ID",
      "pubDate": "2026-04-21T08:18:25.619Z",
      "approxTraffic": "2K+",
      "started": "7 hours ago",
      "source": "browser-scrape"
    },
    {
      "title": "program jaminan kesehatan",
      "link": "https://trends.google.com/trending/rss?geo=ID",
      "pubDate": "2026-04-21T08:18:25.619Z",
      "approxTraffic": "2K+",
      "started": "4 hours ago",
      "source": "browser-scrape"
    },
    {
      "title": "utang pemerintah",
      "link": "https://trends.google.com/trending/rss?geo=ID",
      "pubDate": "2026-04-21T08:18:25.619Z",
      "approxTraffic": "2K+",
      "started": "4 hours ago",
      "source": "browser-scrape"
    },
    {
      "title": "bursa",
      "link": "https://trends.google.com/trending/rss?geo=ID",
      "pubDate": "2026-04-21T08:18:25.619Z",
      "approxTraffic": "1K+",
      "started": "3 hours ago",
      "source": "browser-scrape"
    }
  ]
}
