{
  "source": "google-trends-id",
  "lastUpdated": "2026-05-15T21:09:41.439Z",
  "items": [
    {
      "title": "aston villa vs liverpool",
      "link": "https://trends.google.com/trending/rss?geo=ID",
      "pubDate": "2026-05-15T21:09:41.439Z",
      "approxTraffic": "50K+",
      "started": "15 hours ago",
      "source": "browser-scrape"
    },
    {
      "title": "semen padang vs persebaya",
      "link": "https://trends.google.com/trending/rss?geo=ID",
      "pubDate": "2026-05-15T21:09:41.439Z",
      "approxTraffic": "200K+",
      "started": "15 hours ago",
      "source": "browser-scrape"
    },
    {
      "title": "psbs biak vs arema fc",
      "link": "https://trends.google.com/trending/rss?geo=ID",
      "pubDate": "2026-05-15T21:09:41.439Z",
      "approxTraffic": "100K+",
      "started": "9 hours ago",
      "source": "browser-scrape"
    },
    {
      "title": "film dokumenter pesta babi",
      "link": "https://trends.google.com/trending/rss?geo=ID",
      "pubDate": "2026-05-15T21:09:41.439Z",
      "approxTraffic": "20K+",
      "started": "22 hours ago",
      "source": "browser-scrape"
    },
    {
      "title": "mogok kerja",
      "link": "https://trends.google.com/trending/rss?geo=ID",
      "pubDate": "2026-05-15T21:09:41.439Z",
      "approxTraffic": "10K+",
      "started": "12 hours ago",
      "source": "browser-scrape"
    },
    {
      "title": "didier deschamps",
      "link": "https://trends.google.com/trending/rss?geo=ID",
      "pubDate": "2026-05-15T21:09:41.439Z",
      "approxTraffic": "10K+",
      "started": "23 hours ago",
      "source": "browser-scrape"
    },
    {
      "title": "rupiah ke dollar",
      "link": "https://trends.google.com/trending/rss?geo=ID",
      "pubDate": "2026-05-15T21:09:41.439Z",
      "approxTraffic": "10K+",
      "started": "19 hours ago",
      "source": "browser-scrape"
    },
    {
      "title": "banten",
      "link": "https://trends.google.com/trending/rss?geo=ID",
      "pubDate": "2026-05-15T21:09:41.439Z",
      "approxTraffic": "5K+",
      "started": "15 hours ago",
      "source": "browser-scrape"
    },
    {
      "title": "jang dong ju",
      "link": "https://trends.google.com/trending/rss?geo=ID",
      "pubDate": "2026-05-15T21:09:41.439Z",
      "approxTraffic": "5K+",
      "started": "19 hours ago",
      "source": "browser-scrape"
    },
    {
      "title": "cordoba cf",
      "link": "https://trends.google.com/trending/rss?geo=ID",
      "pubDate": "2026-05-15T21:09:41.439Z",
      "approxTraffic": "2K+",
      "started": "10 hours ago",
      "source": "browser-scrape"
    },
    {
      "title": "piala presiden",
      "link": "https://trends.google.com/trending/rss?geo=ID",
      "pubDate": "2026-05-15T21:09:41.439Z",
      "approxTraffic": "2K+",
      "started": "19 hours ago",
      "source": "browser-scrape"
    },
    {
      "title": "lowongan kerja",
      "link": "https://trends.google.com/trending/rss?geo=ID",
      "pubDate": "2026-05-15T21:09:41.439Z",
      "approxTraffic": "2K+",
      "started": "11 hours ago",
      "source": "browser-scrape"
    },
    {
      "title": "royal antwerp",
      "link": "https://trends.google.com/trending/rss?geo=ID",
      "pubDate": "2026-05-15T21:09:41.439Z",
      "approxTraffic": "2K+",
      "started": "10 hours ago",
      "source": "browser-scrape"
    },
    {
      "title": "al-taawon vs al riyadh",
      "link": "https://trends.google.com/trending/rss?geo=ID",
      "pubDate": "2026-05-15T21:09:41.439Z",
      "approxTraffic": "1K+",
      "started": "3 hours ago",
      "source": "browser-scrape"
    },
    {
      "title": "damac f.c. vs al feiha",
      "link": "https://trends.google.com/trending/rss?geo=ID",
      "pubDate": "2026-05-15T21:09:41.439Z",
      "approxTraffic": "2K+",
      "started": "5 hours ago",
      "source": "browser-scrape"
    }
  ]
}
