{
  "source": "google-trends-id",
  "lastUpdated": "2026-04-17T12:10:22.144Z",
  "items": [
    {
      "title": "bhayangkara fc vs psim",
      "link": "https://trends.google.com/trending/rss?geo=ID",
      "pubDate": "2026-04-17T12:10:22.144Z",
      "approxTraffic": "50K+",
      "started": "4 hours ago",
      "source": "browser-scrape"
    },
    {
      "title": "persebaya vs madura united",
      "link": "https://trends.google.com/trending/rss?geo=ID",
      "pubDate": "2026-04-17T12:10:22.144Z",
      "approxTraffic": "20K+",
      "started": "5 hours ago",
      "source": "browser-scrape"
    },
    {
      "title": "aston villa vs bologna",
      "link": "https://trends.google.com/trending/rss?geo=ID",
      "pubDate": "2026-04-17T12:10:22.144Z",
      "approxTraffic": "100K+",
      "started": "19 hours ago",
      "source": "browser-scrape"
    },
    {
      "title": "betis vs braga",
      "link": "https://trends.google.com/trending/rss?geo=ID",
      "pubDate": "2026-04-17T12:10:22.144Z",
      "approxTraffic": "20K+",
      "started": "18 hours ago",
      "source": "browser-scrape"
    },
    {
      "title": "celta vs freiburg",
      "link": "https://trends.google.com/trending/rss?geo=ID",
      "pubDate": "2026-04-17T12:10:22.144Z",
      "approxTraffic": "20K+",
      "started": "22 hours ago",
      "source": "browser-scrape"
    },
    {
      "title": "aek athena vs rayo",
      "link": "https://trends.google.com/trending/rss?geo=ID",
      "pubDate": "2026-04-17T12:10:22.144Z",
      "approxTraffic": "20K+",
      "started": "18 hours ago",
      "source": "browser-scrape"
    },
    {
      "title": "bernardo silva",
      "link": "https://trends.google.com/trending/rss?geo=ID",
      "pubDate": "2026-04-17T12:10:22.144Z",
      "approxTraffic": "20K+",
      "started": "22 hours ago",
      "source": "browser-scrape"
    },
    {
      "title": "bagikan",
      "link": "https://trends.google.com/trending/rss?geo=ID",
      "pubDate": "2026-04-17T12:10:22.144Z",
      "approxTraffic": "5K+",
      "started": "8 hours ago",
      "source": "browser-scrape"
    },
    {
      "title": "bonus",
      "link": "https://trends.google.com/trending/rss?geo=ID",
      "pubDate": "2026-04-17T12:10:22.144Z",
      "approxTraffic": "5K+",
      "started": "8 hours ago",
      "source": "browser-scrape"
    },
    {
      "title": "99942 apophis",
      "link": "https://trends.google.com/trending/rss?geo=ID",
      "pubDate": "2026-04-17T12:10:22.144Z",
      "approxTraffic": "5K+",
      "started": "23 hours ago",
      "source": "browser-scrape"
    },
    {
      "title": "ketua ombudsman ri hery susanto",
      "link": "https://trends.google.com/trending/rss?geo=ID",
      "pubDate": "2026-04-17T12:10:22.144Z",
      "approxTraffic": "10K+",
      "started": "23 hours ago",
      "source": "browser-scrape"
    },
    {
      "title": "al sadd vs vissel",
      "link": "https://trends.google.com/trending/rss?geo=ID",
      "pubDate": "2026-04-17T12:10:22.144Z",
      "approxTraffic": "10K+",
      "started": "20 hours ago",
      "source": "browser-scrape"
    },
    {
      "title": "az vs shakhtar",
      "link": "https://trends.google.com/trending/rss?geo=ID",
      "pubDate": "2026-04-17T12:10:22.144Z",
      "approxTraffic": "10K+",
      "started": "20 hours ago",
      "source": "browser-scrape"
    },
    {
      "title": "pajak bumi dan bangunan",
      "link": "https://trends.google.com/trending/rss?geo=ID",
      "pubDate": "2026-04-17T12:10:22.144Z",
      "approxTraffic": "2K+",
      "started": "6 hours ago",
      "source": "browser-scrape"
    },
    {
      "title": "helikopter jatuh pk cfx",
      "link": "https://trends.google.com/trending/rss?geo=ID",
      "pubDate": "2026-04-17T12:10:22.144Z",
      "approxTraffic": "5K+",
      "started": "16 hours ago",
      "source": "browser-scrape"
    }
  ]
}
