{
  "source": "google-trends-id",
  "lastUpdated": "2026-04-08T17:41:44.361Z",
  "items": [
    {
      "title": "braga vs betis",
      "link": "https://trends.google.com/trending/rss?geo=ID",
      "pubDate": "2026-04-08T17:41:44.361Z",
      "approxTraffic": "20K+",
      "started": "2 hours ago",
      "source": "browser-scrape"
    },
    {
      "title": "trump gencatan senjata iran",
      "link": "https://trends.google.com/trending/rss?geo=ID",
      "pubDate": "2026-04-08T17:41:44.361Z",
      "approxTraffic": "20K+",
      "started": "12 hours ago",
      "source": "browser-scrape"
    },
    {
      "title": "tempat menonton real madrid vs bayern",
      "link": "https://trends.google.com/trending/rss?geo=ID",
      "pubDate": "2026-04-08T17:41:44.361Z",
      "approxTraffic": "50K+",
      "started": "22 hours ago",
      "source": "browser-scrape"
    },
    {
      "title": "al feiha vs al-ahli saudi",
      "link": "https://trends.google.com/trending/rss?geo=ID",
      "pubDate": "2026-04-08T17:41:44.361Z",
      "approxTraffic": "10K+",
      "started": "2 hours ago",
      "source": "browser-scrape"
    },
    {
      "title": "manuel neuer",
      "link": "https://trends.google.com/trending/rss?geo=ID",
      "pubDate": "2026-04-08T17:41:44.361Z",
      "approxTraffic": "20K+",
      "started": "23 hours ago",
      "source": "browser-scrape"
    },
    {
      "title": "gamba vs bangkok united",
      "link": "https://trends.google.com/trending/rss?geo=ID",
      "pubDate": "2026-04-08T17:41:44.361Z",
      "approxTraffic": "20K+",
      "started": "8 hours ago",
      "source": "browser-scrape"
    },
    {
      "title": "tim nasional sepak bola belanda",
      "link": "https://trends.google.com/trending/rss?geo=ID",
      "pubDate": "2026-04-08T17:41:44.361Z",
      "approxTraffic": "5K+",
      "started": "6 hours ago",
      "source": "browser-scrape"
    },
    {
      "title": "indonesia vs australia futsal",
      "link": "https://trends.google.com/trending/rss?geo=ID",
      "pubDate": "2026-04-08T17:41:44.361Z",
      "approxTraffic": "20K+",
      "started": "12 hours ago",
      "source": "browser-scrape"
    },
    {
      "title": "lafc vs cruz azul",
      "link": "https://trends.google.com/trending/rss?geo=ID",
      "pubDate": "2026-04-08T17:41:44.361Z",
      "approxTraffic": "10K+",
      "started": "16 hours ago",
      "source": "browser-scrape"
    },
    {
      "title": "göztepe vs galatasaray",
      "link": "https://trends.google.com/trending/rss?geo=ID",
      "pubDate": "2026-04-08T17:41:44.361Z",
      "approxTraffic": "2K+",
      "started": "1 hour ago",
      "source": "browser-scrape"
    },
    {
      "title": "sinetron turun ranjang",
      "link": "https://trends.google.com/trending/rss?geo=ID",
      "pubDate": "2026-04-08T17:41:44.361Z",
      "approxTraffic": "2K+",
      "started": "12 hours ago",
      "source": "browser-scrape"
    },
    {
      "title": "piala dunia fifa 2026",
      "link": "https://trends.google.com/trending/rss?geo=ID",
      "pubDate": "2026-04-08T17:41:44.361Z",
      "approxTraffic": "10K+",
      "started": "9 hours ago",
      "source": "browser-scrape"
    },
    {
      "title": "braga",
      "link": "https://trends.google.com/trending/rss?geo=ID",
      "pubDate": "2026-04-08T17:41:44.361Z",
      "approxTraffic": "2K+",
      "started": "8 hours ago",
      "source": "browser-scrape"
    },
    {
      "title": "mati listrik",
      "link": "https://trends.google.com/trending/rss?geo=ID",
      "pubDate": "2026-04-08T17:41:44.361Z",
      "approxTraffic": "5K+",
      "started": "18 hours ago",
      "source": "browser-scrape"
    },
    {
      "title": "aplikasi cek bansos",
      "link": "https://trends.google.com/trending/rss?geo=ID",
      "pubDate": "2026-04-08T17:41:44.361Z",
      "approxTraffic": "5K+",
      "started": "5 hours ago",
      "source": "browser-scrape"
    }
  ]
}
