{
  "source": "google-trends-id",
  "lastUpdated": "2026-05-10T14:00:40.578Z",
  "items": [
    {
      "title": "man city vs brentford",
      "link": "https://trends.google.com/trending/rss?geo=ID",
      "pubDate": "2026-05-10T14:00:40.578Z",
      "approxTraffic": "200K+",
      "started": "23 hours ago",
      "source": "browser-scrape"
    },
    {
      "title": "skor persib vs persija",
      "link": "https://trends.google.com/trending/rss?geo=ID",
      "pubDate": "2026-05-10T14:00:40.578Z",
      "approxTraffic": "500K+",
      "started": "6 hours ago",
      "source": "browser-scrape"
    },
    {
      "title": "psim vs malut united",
      "link": "https://trends.google.com/trending/rss?geo=ID",
      "pubDate": "2026-05-10T14:00:40.578Z",
      "approxTraffic": "20K+",
      "started": "2 hours ago",
      "source": "browser-scrape"
    },
    {
      "title": "hari ibu tanggal berapa 2026",
      "link": "https://trends.google.com/trending/rss?geo=ID",
      "pubDate": "2026-05-10T14:00:40.578Z",
      "approxTraffic": "50K+",
      "started": "17 hours ago",
      "source": "browser-scrape"
    },
    {
      "title": "burnley vs aston villa",
      "link": "https://trends.google.com/trending/rss?geo=ID",
      "pubDate": "2026-05-10T14:00:40.578Z",
      "approxTraffic": "20K+",
      "started": "1 hour ago",
      "source": "browser-scrape"
    },
    {
      "title": "verona vs como",
      "link": "https://trends.google.com/trending/rss?geo=ID",
      "pubDate": "2026-05-10T14:00:40.578Z",
      "approxTraffic": "20K+",
      "started": "4 hours ago",
      "source": "browser-scrape"
    },
    {
      "title": "atlético madrid vs celta",
      "link": "https://trends.google.com/trending/rss?geo=ID",
      "pubDate": "2026-05-10T14:00:40.578Z",
      "approxTraffic": "50K+",
      "started": "22 hours ago",
      "source": "browser-scrape"
    },
    {
      "title": "persita vs persijap",
      "link": "https://trends.google.com/trending/rss?geo=ID",
      "pubDate": "2026-05-10T14:00:40.578Z",
      "approxTraffic": "50K+",
      "started": "6 hours ago",
      "source": "browser-scrape"
    },
    {
      "title": "wolfsburg vs bayern",
      "link": "https://trends.google.com/trending/rss?geo=ID",
      "pubDate": "2026-05-10T14:00:40.578Z",
      "approxTraffic": "50K+",
      "started": "22 hours ago",
      "source": "browser-scrape"
    },
    {
      "title": "lazio vs inter",
      "link": "https://trends.google.com/trending/rss?geo=ID",
      "pubDate": "2026-05-10T14:00:40.578Z",
      "approxTraffic": "50K+",
      "started": "22 hours ago",
      "source": "browser-scrape"
    },
    {
      "title": "toronto fc vs inter miami",
      "link": "https://trends.google.com/trending/rss?geo=ID",
      "pubDate": "2026-05-10T14:00:40.578Z",
      "approxTraffic": "50K+",
      "started": "21 hours ago",
      "source": "browser-scrape"
    },
    {
      "title": "crystal palace vs everton",
      "link": "https://trends.google.com/trending/rss?geo=ID",
      "pubDate": "2026-05-10T14:00:40.578Z",
      "approxTraffic": "10K+",
      "started": "6 hours ago",
      "source": "browser-scrape"
    },
    {
      "title": "lecce vs juventus",
      "link": "https://trends.google.com/trending/rss?geo=ID",
      "pubDate": "2026-05-10T14:00:40.578Z",
      "approxTraffic": "20K+",
      "started": "22 hours ago",
      "source": "browser-scrape"
    },
    {
      "title": "nottingham forest vs newcastle",
      "link": "https://trends.google.com/trending/rss?geo=ID",
      "pubDate": "2026-05-10T14:00:40.578Z",
      "approxTraffic": "10K+",
      "started": "1 hour ago",
      "source": "browser-scrape"
    },
    {
      "title": "cremonese vs pisa",
      "link": "https://trends.google.com/trending/rss?geo=ID",
      "pubDate": "2026-05-10T14:00:40.578Z",
      "approxTraffic": "10K+",
      "started": "1 hour ago",
      "source": "browser-scrape"
    }
  ]
}
