{
  "source": "google-trends-id",
  "lastUpdated": "2026-04-30T15:28:18.906Z",
  "items": [
    {
      "title": "bhayangkara fc vs persib bandung",
      "link": "https://trends.google.com/trending/rss?geo=ID",
      "pubDate": "2026-04-30T15:28:18.906Z",
      "approxTraffic": "500K+",
      "started": "6 hours ago",
      "source": "browser-scrape"
    },
    {
      "title": "al-nassr vs al-ahli saudi",
      "link": "https://trends.google.com/trending/rss?geo=ID",
      "pubDate": "2026-04-30T15:28:18.906Z",
      "approxTraffic": "200K+",
      "started": "22 hours ago",
      "source": "browser-scrape"
    },
    {
      "title": "psim vs persita",
      "link": "https://trends.google.com/trending/rss?geo=ID",
      "pubDate": "2026-04-30T15:28:18.906Z",
      "approxTraffic": "50K+",
      "started": "9 hours ago",
      "source": "browser-scrape"
    },
    {
      "title": "sporting cp vs tondela",
      "link": "https://trends.google.com/trending/rss?geo=ID",
      "pubDate": "2026-04-30T15:28:18.906Z",
      "approxTraffic": "20K+",
      "started": "20 hours ago",
      "source": "browser-scrape"
    },
    {
      "title": "wakil presiden filipina",
      "link": "https://trends.google.com/trending/rss?geo=ID",
      "pubDate": "2026-04-30T15:28:18.906Z",
      "approxTraffic": "20K+",
      "started": "22 hours ago",
      "source": "browser-scrape"
    },
    {
      "title": "atlético madrid vs arsenal fc",
      "link": "https://trends.google.com/trending/rss?geo=ID",
      "pubDate": "2026-04-30T15:28:18.906Z",
      "approxTraffic": "100K+",
      "started": "13 hours ago",
      "source": "browser-scrape"
    },
    {
      "title": "klasemen liga 1",
      "link": "https://trends.google.com/trending/rss?geo=ID",
      "pubDate": "2026-04-30T15:28:18.906Z",
      "approxTraffic": "50K+",
      "started": "2 hours ago",
      "source": "browser-scrape"
    },
    {
      "title": "1 mei apakah tanggal merah",
      "link": "https://trends.google.com/trending/rss?geo=ID",
      "pubDate": "2026-04-30T15:28:18.906Z",
      "approxTraffic": "20K+",
      "started": "16 hours ago",
      "source": "browser-scrape"
    },
    {
      "title": "maruarar sirait",
      "link": "https://trends.google.com/trending/rss?geo=ID",
      "pubDate": "2026-04-30T15:28:18.906Z",
      "approxTraffic": "5K+",
      "started": "18 hours ago",
      "source": "browser-scrape"
    },
    {
      "title": "arsenal w.f.c. vs leicester city w.f.c.",
      "link": "https://trends.google.com/trending/rss?geo=ID",
      "pubDate": "2026-04-30T15:28:18.906Z",
      "approxTraffic": "10K+",
      "started": "21 hours ago",
      "source": "browser-scrape"
    },
    {
      "title": "pembagian dividen bmri",
      "link": "https://trends.google.com/trending/rss?geo=ID",
      "pubDate": "2026-04-30T15:28:18.906Z",
      "approxTraffic": "10K+",
      "started": "23 hours ago",
      "source": "browser-scrape"
    },
    {
      "title": "andre taulany",
      "link": "https://trends.google.com/trending/rss?geo=ID",
      "pubDate": "2026-04-30T15:28:18.906Z",
      "approxTraffic": "2K+",
      "started": "14 hours ago",
      "source": "browser-scrape"
    },
    {
      "title": "megawati hangestri pertiwi",
      "link": "https://trends.google.com/trending/rss?geo=ID",
      "pubDate": "2026-04-30T15:28:18.906Z",
      "approxTraffic": "5K+",
      "started": "6 hours ago",
      "source": "browser-scrape"
    },
    {
      "title": "pelaporan spt tahunan badan",
      "link": "https://trends.google.com/trending/rss?geo=ID",
      "pubDate": "2026-04-30T15:28:18.906Z",
      "approxTraffic": "20K+",
      "started": "4 hours ago",
      "source": "browser-scrape"
    },
    {
      "title": "lafc vs toluca",
      "link": "https://trends.google.com/trending/rss?geo=ID",
      "pubDate": "2026-04-30T15:28:18.906Z",
      "approxTraffic": "5K+",
      "started": "13 hours ago",
      "source": "browser-scrape"
    }
  ]
}
