{
  "source": "google-trends-id",
  "lastUpdated": "2026-05-19T08:15:33.012Z",
  "items": [
    {
      "title": "spurs vs thunder",
      "link": "https://trends.google.com/trending/rss?geo=ID",
      "pubDate": "2026-05-19T08:15:33.012Z",
      "approxTraffic": "20K+",
      "started": "7 hours ago",
      "source": "browser-scrape"
    },
    {
      "title": "listyo sigit prabowo",
      "link": "https://trends.google.com/trending/rss?geo=ID",
      "pubDate": "2026-05-19T08:15:33.012Z",
      "approxTraffic": "10K+",
      "started": "21 hours ago",
      "source": "browser-scrape"
    },
    {
      "title": "pagi sore",
      "link": "https://trends.google.com/trending/rss?geo=ID",
      "pubDate": "2026-05-19T08:15:33.012Z",
      "approxTraffic": "5K+",
      "started": "21 hours ago",
      "source": "browser-scrape"
    },
    {
      "title": "dollar to rupiah",
      "link": "https://trends.google.com/trending/rss?geo=ID",
      "pubDate": "2026-05-19T08:15:33.012Z",
      "approxTraffic": "50K+",
      "started": "5 hours ago",
      "source": "browser-scrape"
    },
    {
      "title": "ihsg",
      "link": "https://trends.google.com/trending/rss?geo=ID",
      "pubDate": "2026-05-19T08:15:33.012Z",
      "approxTraffic": "20K+",
      "started": "3 hours ago",
      "source": "browser-scrape"
    },
    {
      "title": "bank central asia",
      "link": "https://trends.google.com/trending/rss?geo=ID",
      "pubDate": "2026-05-19T08:15:33.012Z",
      "approxTraffic": "5K+",
      "started": "21 hours ago",
      "source": "browser-scrape"
    },
    {
      "title": "hari kebangkitan nasional 2026",
      "link": "https://trends.google.com/trending/rss?geo=ID",
      "pubDate": "2026-05-19T08:15:33.012Z",
      "approxTraffic": "5K+",
      "started": "7 hours ago",
      "source": "browser-scrape"
    },
    {
      "title": "pakistan",
      "link": "https://trends.google.com/trending/rss?geo=ID",
      "pubDate": "2026-05-19T08:15:33.012Z",
      "approxTraffic": "2K+",
      "started": "6 hours ago",
      "source": "browser-scrape"
    },
    {
      "title": "joao pedro",
      "link": "https://trends.google.com/trending/rss?geo=ID",
      "pubDate": "2026-05-19T08:15:33.012Z",
      "approxTraffic": "2K+",
      "started": "8 hours ago",
      "source": "browser-scrape"
    },
    {
      "title": "bitcoin",
      "link": "https://trends.google.com/trending/rss?geo=ID",
      "pubDate": "2026-05-19T08:15:33.012Z",
      "approxTraffic": "2K+",
      "started": "50 minutes ago",
      "source": "browser-scrape"
    },
    {
      "title": "cesc fabregas",
      "link": "https://trends.google.com/trending/rss?geo=ID",
      "pubDate": "2026-05-19T08:15:33.012Z",
      "approxTraffic": "5K+",
      "started": "16 hours ago",
      "source": "browser-scrape"
    },
    {
      "title": "mati listrik",
      "link": "https://trends.google.com/trending/rss?geo=ID",
      "pubDate": "2026-05-19T08:15:33.012Z",
      "approxTraffic": "2K+",
      "started": "5 hours ago",
      "source": "browser-scrape"
    },
    {
      "title": "dosen",
      "link": "https://trends.google.com/trending/rss?geo=ID",
      "pubDate": "2026-05-19T08:15:33.012Z",
      "approxTraffic": "1K+",
      "started": "3 hours ago",
      "source": "browser-scrape"
    },
    {
      "title": "ramalan shio",
      "link": "https://trends.google.com/trending/rss?geo=ID",
      "pubDate": "2026-05-19T08:15:33.012Z",
      "approxTraffic": "2K+",
      "started": "11 hours ago",
      "source": "browser-scrape"
    },
    {
      "title": "pencairan bpnt bertahap",
      "link": "https://trends.google.com/trending/rss?geo=ID",
      "pubDate": "2026-05-19T08:15:33.012Z",
      "approxTraffic": "2K+",
      "started": "16 hours ago",
      "source": "browser-scrape"
    }
  ]
}
