{
  "source": "google-trends-id",
  "lastUpdated": "2026-06-13T01:30:29.887Z",
  "items": [
    {
      "title": "amerika serikat vs paraguay",
      "link": "https://trends.google.com/trending/rss?geo=ID",
      "pubDate": "2026-06-13T01:30:29.887Z",
      "approxTraffic": "20K+",
      "started": "6 hours ago",
      "source": "browser-scrape"
    },
    {
      "title": "hwang in-beom",
      "link": "https://trends.google.com/trending/rss?geo=ID",
      "pubDate": "2026-06-13T01:30:29.887Z",
      "approxTraffic": "20K+",
      "started": "23 hours ago",
      "source": "browser-scrape"
    },
    {
      "title": "kanada vs bosnia",
      "link": "https://trends.google.com/trending/rss?geo=ID",
      "pubDate": "2026-06-13T01:30:29.887Z",
      "approxTraffic": "20K+",
      "started": "8 hours ago",
      "source": "browser-scrape"
    },
    {
      "title": "usa vs paraguay",
      "link": "https://trends.google.com/trending/rss?geo=ID",
      "pubDate": "2026-06-13T01:30:29.887Z",
      "approxTraffic": "10K+",
      "started": "5 hours ago",
      "source": "browser-scrape"
    },
    {
      "title": "presiden",
      "link": "https://trends.google.com/trending/rss?geo=ID",
      "pubDate": "2026-06-13T01:30:29.887Z",
      "approxTraffic": "10K+",
      "started": "19 hours ago",
      "source": "browser-scrape"
    },
    {
      "title": "canada",
      "link": "https://trends.google.com/trending/rss?geo=ID",
      "pubDate": "2026-06-13T01:30:29.887Z",
      "approxTraffic": "20K+",
      "started": "7 hours ago",
      "source": "browser-scrape"
    },
    {
      "title": "jadwal piala dunia hari ini",
      "link": "https://trends.google.com/trending/rss?geo=ID",
      "pubDate": "2026-06-13T01:30:29.887Z",
      "approxTraffic": "5K+",
      "started": "14 hours ago",
      "source": "browser-scrape"
    },
    {
      "title": "peringkat",
      "link": "https://trends.google.com/trending/rss?geo=ID",
      "pubDate": "2026-06-13T01:30:29.887Z",
      "approxTraffic": "10K+",
      "started": "16 hours ago",
      "source": "browser-scrape"
    },
    {
      "title": "ragnar oratmangoen",
      "link": "https://trends.google.com/trending/rss?geo=ID",
      "pubDate": "2026-06-13T01:30:29.887Z",
      "approxTraffic": "5K+",
      "started": "13 hours ago",
      "source": "browser-scrape"
    },
    {
      "title": "jennifer coppen",
      "link": "https://trends.google.com/trending/rss?geo=ID",
      "pubDate": "2026-06-13T01:30:29.887Z",
      "approxTraffic": "5K+",
      "started": "17 hours ago",
      "source": "browser-scrape"
    },
    {
      "title": "makan bergizi gratis",
      "link": "https://trends.google.com/trending/rss?geo=ID",
      "pubDate": "2026-06-13T01:30:29.887Z",
      "approxTraffic": "5K+",
      "started": "20 hours ago",
      "source": "browser-scrape"
    },
    {
      "title": "folarin balogun",
      "link": "https://trends.google.com/trending/rss?geo=ID",
      "pubDate": "2026-06-13T01:30:29.887Z",
      "approxTraffic": "1K+",
      "started": "1 hour ago",
      "source": "browser-scrape"
    },
    {
      "title": "brazil vs morocco",
      "link": "https://trends.google.com/trending/rss?geo=ID",
      "pubDate": "2026-06-13T01:30:29.887Z",
      "approxTraffic": "1K+",
      "started": "4 hours ago",
      "source": "browser-scrape"
    },
    {
      "title": "sergiño dest",
      "link": "https://trends.google.com/trending/rss?geo=ID",
      "pubDate": "2026-06-13T01:30:29.887Z",
      "approxTraffic": "1K+",
      "started": "1 hour ago",
      "source": "browser-scrape"
    },
    {
      "title": "brasil vs maroko",
      "link": "https://trends.google.com/trending/rss?geo=ID",
      "pubDate": "2026-06-13T01:30:29.887Z",
      "approxTraffic": "2K+",
      "started": "4 hours ago",
      "source": "browser-scrape"
    }
  ]
}
